httpprep/Headers.py
httpprep/OverloadDict.py
httpprep/URL.py
httpprep/__init__.py
http_prep-0.0.6.dist-info/LICENSE
http_prep-0.0.6.dist-info/METADATA
http_prep-0.0.6.dist-info/WHEEL
http_prep-0.0.6.dist-info/top_level.txt
http_prep-0.0.6.dist-info/RECORD
