Metadata-Version: 2.1
Name: http-prep
Version: 0.0.6
Summary: A tool to easily create complicated and dynamic URLs and headers
Author-email: "Tanner B. Corcoran" <tannerbcorcoran@gmail.com>
Project-URL: Homepage, https://github.com/tanrbobanr/http-prep
Classifier: Programming Language :: Python :: 3
Classifier: License :: OSI Approved :: MIT License
Classifier: Operating System :: OS Independent
Requires-Python: >=3.7.9
License-File: LICENSE
Requires-Dist: prepr (>=0.0.6)
